winrollex/__init__.py
winrollex/window.py
winrollex-0.1.1.dist-info/LICENSE
winrollex-0.1.1.dist-info/METADATA
winrollex-0.1.1.dist-info/WHEEL
winrollex-0.1.1.dist-info/RECORD
