Metadata-Version: 2.1
Name: winrollex
Version: 0.1.1
Summary: Simple [temporal] rolling and expanding windows for machine learning applicationsn
Home-page: https://github.com/ArthurMatta/WinRollEx
License: MIT
Author: Arthur Matta
Author-email: arthur.matta@ccg.pt
Requires-Python: >=3.10,<4
Classifier: Development Status :: 3 - Alpha
Classifier: Intended Audience :: Developers
Classifier: License :: OSI Approved :: MIT License
Classifier: Operating System :: OS Independent
Classifier: Programming Language :: Python :: 3
Classifier: Programming Language :: Python :: 3.10
Classifier: Programming Language :: Python :: 3.11
Classifier: Programming Language :: Python :: 3.12
Classifier: Topic :: Scientific/Engineering :: Artificial Intelligence
Classifier: Topic :: Software Development :: Libraries :: Python Modules
Requires-Dist: numpy (>=2.0.0,<3.0.0)
Requires-Dist: pandas (>=2.0.0,<3.0.0)
Requires-Dist: python-dateutil (>=2.9.0.post0,<3.0.0)
Project-URL: Bug Tracker, https://github.com/ArthurMatta/WinRollEx/issues
Project-URL: Repository, https://github.com/ArthurMatta/WinRollEx
